streamlit_doubutsushogi/__init__.py
streamlit_doubutsushogi/frontend/build/asset-manifest.json
streamlit_doubutsushogi/frontend/build/bootstrap.min.css
streamlit_doubutsushogi/frontend/build/doubutsushogi.css
streamlit_doubutsushogi/frontend/build/index.html
streamlit_doubutsushogi/frontend/build/precache-manifest.94e4c3dd1fc70e61fb2bb4ada41e3a83.js
streamlit_doubutsushogi/frontend/build/service-worker.js
streamlit_doubutsushogi/frontend/build/static/js/2.85dae30a.chunk.js
streamlit_doubutsushogi/frontend/build/static/js/2.85dae30a.chunk.js.LICENSE.txt
streamlit_doubutsushogi/frontend/build/static/js/2.85dae30a.chunk.js.map
streamlit_doubutsushogi/frontend/build/static/js/main.23be9abc.chunk.js
streamlit_doubutsushogi/frontend/build/static/js/main.23be9abc.chunk.js.map
streamlit_doubutsushogi/frontend/build/static/js/runtime-main.44d30fc2.js
streamlit_doubutsushogi/frontend/build/static/js/runtime-main.44d30fc2.js.map
streamlit_doubutsushogi-0.0.21.dist-info/LICENSE
streamlit_doubutsushogi-0.0.21.dist-info/METADATA
streamlit_doubutsushogi-0.0.21.dist-info/WHEEL
streamlit_doubutsushogi-0.0.21.dist-info/top_level.txt
streamlit_doubutsushogi-0.0.21.dist-info/RECORD
