Metadata-Version: 2.1
Name: streamlit-doubutsushogi
Version: 0.0.21
Summary: A streamlit custom component for doubutsushogi (animal chess) game
Home-page: UNKNOWN
Author: Kota Mori
Author-email: kmori05@gmail.com
License: UNKNOWN
Platform: UNKNOWN
Requires-Python: >=3.6
License-File: LICENSE
Requires-Dist: doubutsushogi
Requires-Dist: streamlit >=0.63
